RUST/RUST_amino.py
RUST/RUST_codon.py
RUST/RUST_dipeptide.py
RUST/RUST_nucleotide.py
RUST/RUST_tripeptide.py
RUST/__init__.py
RUST/footprint_codons.py
RUST/observed_expected.py
RUST/synergy_31.py
RUST-0.1.0.dist-info/DESCRIPTION.rst
RUST-0.1.0.dist-info/METADATA
RUST-0.1.0.dist-info/RECORD
RUST-0.1.0.dist-info/WHEEL
RUST-0.1.0.dist-info/metadata.json
RUST-0.1.0.dist-info/top_level.txt
