Metadata-Version: 2.0
Name: RUST
Version: 0.1.0
Summary: Ribo-Seq Unit Step Transformation
Home-page: http://ribogalaxy.ucc.ie
Author: Patrick O'Connor
Author-email: patrickoconnor215@gmail.com
License: GPL
Keywords: rust ribo-seq ribosome profiling
Platform: UNKNOWN
Classifier: Development Status :: 5 - Production/Stable
Classifier: Intended Audience :: Science/Research
Classifier: Topic :: Scientific/Engineering :: Bio-Informatics
Classifier: License :: OSI Approved :: GNU General Public License (GPL)
Classifier: Programming Language :: Python :: 2
Classifier: Programming Language :: Python :: 2.6
Classifier: Programming Language :: Python :: 2.7
Requires-Dist: biopython
Requires-Dist: matplotlib
Requires-Dist: pysam
